README.txt
setup.py
vmrun_wrapper/__init__.py
vmrun_wrapper.egg-info/PKG-INFO
vmrun_wrapper.egg-info/SOURCES.txt
vmrun_wrapper.egg-info/dependency_links.txt
vmrun_wrapper.egg-info/top_level.txt
vmrun_wrapper/tests/__init__.py
vmrun_wrapper/tests/vmrun.py
vmrun_wrapper/vmrun/__init__.py
vmrun_wrapper/vmrun/errors.py
vmrun_wrapper/vmrun/machine.py
vmrun_wrapper/vmrun/snapshots.py