Metadata-Version: 1.0
Name: vmrun-wrapper
Version: 1.1
Summary: a wrapper for the VMWare Fusion's vmrun utility.
Home-page: https://github.com/k3rn/vmrun-wrapper
Author: Mateus Kern
Author-email: kern@mateuskern.com
License: MIT
Platform: UNKNOWN
